[
    {
        "name": "Id",
        "dbType": "integer,true",
        "htmlType": null,
        "validations": null,
        "searchable": false,
        "fillable": false,
        "primary": true,
        "inForm": false,
        "inIndex": false,
        "inView": false
    },
    {
        "name": "SessionId",
        "dbType": "integer,false",
        "htmlType": null,
        "validations": "nullable|integer",
        "searchable": true,
        "fillable": true,
        "primary": false,
        "inForm": true,
        "inIndex": true,
        "inView": true
    },
    {
        "name": "RequestType",
        "dbType": "string,50:nullable",
        "htmlType": "text",
        "validations": "nullable|string|max:50",
        "searchable": true,
        "fillable": true,
        "primary": false,
        "inForm": true,
        "inIndex": true,
        "inView": true
    },
    {
        "name": "RequestBody",
        "dbType": "text:nullable",
        "htmlType": "textarea",
        "validations": "nullable|string",
        "searchable": true,
        "fillable": true,
        "primary": false,
        "inForm": true,
        "inIndex": true,
        "inView": true
    },
    {
        "name": "RequestDate",
        "dbType": "datetime:nullable",
        "htmlType": "date",
        "validations": "nullable",
        "searchable": true,
        "fillable": true,
        "primary": false,
        "inForm": true,
        "inIndex": true,
        "inView": true
    },
    {
        "name": "ResponseBody",
        "dbType": "text:nullable",
        "htmlType": "textarea",
        "validations": "nullable|string",
        "searchable": true,
        "fillable": true,
        "primary": false,
        "inForm": true,
        "inIndex": true,
        "inView": true
    },
    {
        "name": "ResponseDate",
        "dbType": "datetime:nullable",
        "htmlType": "date",
        "validations": "nullable",
        "searchable": true,
        "fillable": true,
        "primary": false,
        "inForm": true,
        "inIndex": true,
        "inView": true
    },
    {
        "name": "Status",
        "dbType": "string,20:nullable",
        "htmlType": "text",
        "validations": "nullable|string|max:20",
        "searchable": true,
        "fillable": true,
        "primary": false,
        "inForm": true,
        "inIndex": true,
        "inView": true
    },
    {
        "name": "TransactionId",
        "dbType": "string,50:nullable",
        "htmlType": "text",
        "validations": "nullable|string|max:50",
        "searchable": true,
        "fillable": true,
        "primary": false,
        "inForm": true,
        "inIndex": true,
        "inView": true
    },
    {
        "name": "CallbackResponse",
        "dbType": "text:nullable",
        "htmlType": "textarea",
        "validations": "nullable|string",
        "searchable": true,
        "fillable": true,
        "primary": false,
        "inForm": true,
        "inIndex": true,
        "inView": true
    }
]